{"count": 55547486, "first": "https://hubeau.eaufrance.fr/api/v1/hydrometrie/observations_tr?cursor=&size=100", "prev": null, "next": "https://hubeau.eaufrance.fr/api/v1/hydrometrie/observations_tr?cursor=AoJwxr6qgpIDPwxZMDQ0NTAxMF9ZMDQ0NTAxMDAxX0hfNF8yMDI0LTA5LTE4VDEwOjI1OjAw&size=100", "api_version": "1.0.1", "data": [{"code_site": "P1592510", "code_station": "P159251001", "grandeur_hydro": "H", "date_debut_serie": "2024-09-18T00:00:01Z", "date_fin_serie": "2024-09-18T10:25:00Z", "statut_serie": 4, "code_systeme_alti_serie": 31, "date_obs": "2024-09-18T10:25:00Z", "resultat_obs": 769.0, "code_methode_obs": 0, "libelle_methode_obs": "Mesure", "code_qualification_obs": 16, "libelle_qualification_obs": "Non qualifi\u00e9e", "continuite_obs_hydro": true, "longitude": 1.946271799, "latitude": 45.083437105}, {"code_site": "P1592510", "code_station": "P159251001", "grandeur_hydro": "Q", "date_debut_serie": "2024-09-18T00:00:01Z", "date_fin_serie": "2024-09-18T10:25:00Z", "statut_serie": 4, "code_systeme_alti_serie": 31, "date_obs": "2024-09-18T10:25:00Z", "resultat_obs": 2060.0, "code_methode_obs": 12, "libelle_methode_obs": "Interpolation", "code_qualification_obs": 16, "libelle_qualification_obs": "Non qualifi\u00e9e", "continuite_obs_hydro": true, "longitude": 1.946271799, "latitude": 45.083437105}, {"code_site": "P1592510", "code_station": null, "grandeur_hydro": "Q", "date_debut_serie": "2024-09-18T00:00:01Z", "date_fin_serie": "2024-09-18T10:25:00Z", "statut_serie": 4, "code_systeme_alti_serie": 31, "date_obs": "2024-09-18T10:25:00Z", "resultat_obs": 2060.0, "code_methode_obs": 12, "libelle_methode_obs": "Interpolation", "code_qualification_obs": 16, "libelle_qualification_obs": "Non qualifi\u00e9e", "continuite_obs_hydro": true, "longitude": 1.946271799, "latitude": 45.083437105}, {"code_site": "P2315020", "code_station": "P231502001", "grandeur_hydro": "H", "date_debut_serie": "2024-09-18T00:15:00Z", "date_fin_serie": "2024-09-18T10:25:00Z", "statut_serie": 4, "code_systeme_alti_serie": 31, "date_obs": "2024-09-18T10:25:00Z", "resultat_obs": 513.0, "code_methode_obs": 0, "libelle_methode_obs": "Mesure", "code_qualification_obs": 16, "libelle_qualification_obs": "Non qualifi\u00e9e", "continuite_obs_hydro": true, "longitude": 1.471574846, "latitude": 44.907627338}, {"code_site": "P2315020", "code_station": "P231502001", "grandeur_hydro": "Q", "date_debut_serie": "2024-09-18T00:15:00Z", "date_fin_serie": "2024-09-18T10:25:00Z", "statut_serie": 4, "code_systeme_alti_serie": 31, "date_obs": "2024-09-18T10:25:00Z", "resultat_obs": 462.0, "code_methode_obs": 12, "libelle_methode_obs": "Interpolation", "code_qualification_obs": 16, "libelle_qualification_obs": "Non qualifi\u00e9e", "continuite_obs_hydro": true, "longitude": 1.471574846, "latitude": 44.907627338}, {"code_site": "P2315020", "code_station": null, "grandeur_hydro": "Q", "date_debut_serie": "2024-09-18T00:15:00Z", "date_fin_serie": "2024-09-18T10:25:00Z", "statut_serie": 4, "code_systeme_alti_serie": 31, "date_obs": "2024-09-18T10:25:00Z", "resultat_obs": 462.0, "code_methode_obs": 12, "libelle_methode_obs": "Interpolation", "code_qualification_obs": 16, "libelle_qualification_obs": "Non qualifi\u00e9e", "continuite_obs_hydro": true, "longitude": 1.471574846, "latitude": 44.907627338}, {"code_site": "P3031010", "code_station": "P303101001", "grandeur_hydro": "H", "date_debut_serie": "2024-09-18T09:10:00Z", "date_fin_serie": "2024-09-18T10:25:00Z", "statut_serie": 4, "code_systeme_alti_serie": 31, "date_obs": "2024-09-18T10:25:00Z", "resultat_obs": 350.0, "code_methode_obs": 0, "libelle_methode_obs": "Mesure", "code_qualification_obs": 16, "libelle_qualification_obs": "Non qualifi\u00e9e", "continuite_obs_hydro": true, "longitude": 1.838164857, "latitude": 45.576235439}, {"code_site": "P3101010", "code_station": "P310101001", "grandeur_hydro": "H", "date_debut_serie": "2024-09-18T00:00:01Z", "date_fin_serie": "2024-09-18T10:25:00Z", "statut_serie": 4, "code_systeme_alti_serie": 31, "date_obs": "2024-09-18T10:25:00Z", "resultat_obs": 714.0, "code_methode_obs": 0, "libelle_methode_obs": "Mesure", "code_qualification_obs": 16, "libelle_qualification_obs": "Non qualifi\u00e9e", "continuite_obs_hydro": true, "longitude": 1.706982481, "latitude": 45.500639523}, {"code_site": "P3101010", "code_station": "P310101001", "grandeur_hydro": "Q", "date_debut_serie": "2024-09-18T00:00:01Z", "date_fin_serie": "2024-09-18T10:25:00Z", "statut_serie": 4, "code_systeme_alti_serie": 31, "date_obs": "2024-09-18T10:25:00Z", "resultat_obs": 3600.0, "code_methode_obs": 12, "libelle_methode_obs": "Interpolation", "code_qualification_obs": 16, "libelle_qualification_obs": "Non qualifi\u00e9e", "continuite_obs_hydro": true, "longitude": 1.706982481, "latitude": 45.500639523}, {"code_site": "P3101010", "code_station": null, "grandeur_hydro": "Q", "date_debut_serie": "2024-09-18T00:00:01Z", "date_fin_serie": "2024-09-18T10:25:00Z", "statut_serie": 4, "code_systeme_alti_serie": 31, "date_obs": "2024-09-18T10:25:00Z", "resultat_obs": 3600.0, "code_methode_obs": 12, "libelle_methode_obs": "Interpolation", "code_qualification_obs": 16, "libelle_qualification_obs": "Non qualifi\u00e9e", "continuite_obs_hydro": true, "longitude": 1.706982481, "latitude": 45.500639523}, {"code_site": "P3352520", "code_station": "P335252001", "grandeur_hydro": "H", "date_debut_serie": "2024-09-18T00:00:01Z", "date_fin_serie": "2024-09-18T10:25:00Z", "statut_serie": 4, "code_systeme_alti_serie": 31, "date_obs": "2024-09-18T10:25:00Z", "resultat_obs": 927.0, "code_methode_obs": 0, "libelle_methode_obs": "Mesure", "code_qualification_obs": 16, "libelle_qualification_obs": "Non qualifi\u00e9e", "continuite_obs_hydro": true, "longitude": 1.880202647, "latitude": 45.372317288}, {"code_site": "P3352520", "code_station": "P335252001", "grandeur_hydro": "Q", "date_debut_serie": "2024-09-18T00:00:01Z", "date_fin_serie": "2024-09-18T10:25:00Z", "statut_serie": 4, "code_systeme_alti_serie": 31, "date_obs": "2024-09-18T10:25:00Z", "resultat_obs": 1110.0, "code_methode_obs": 12, "libelle_methode_obs": "Interpolation", "code_qualification_obs": 16, "libelle_qualification_obs": "Non qualifi\u00e9e", "continuite_obs_hydro": true, "longitude": 1.880202647, "latitude": 45.372317288}, {"code_site": "P3352520", "code_station": null, "grandeur_hydro": "Q", "date_debut_serie": "2024-09-18T00:00:01Z", "date_fin_serie": "2024-09-18T10:25:00Z", "statut_serie": 4, "code_systeme_alti_serie": 31, "date_obs": "2024-09-18T10:25:00Z", "resultat_obs": 1110.0, "code_methode_obs": 12, "libelle_methode_obs": "Interpolation", "code_qualification_obs": 16, "libelle_qualification_obs": "Non qualifi\u00e9e", "continuite_obs_hydro": true, "longitude": 1.880202647, "latitude": 45.372317288}, {"code_site": "P3840101", "code_station": "P384010101", "grandeur_hydro": "H", "date_debut_serie": "2024-09-18T00:00:01Z", "date_fin_serie": "2024-09-18T10:25:00Z", "statut_serie": 4, "code_systeme_alti_serie": 31, "date_obs": "2024-09-18T10:25:00Z", "resultat_obs": 195.0, "code_methode_obs": 0, "libelle_methode_obs": "Mesure", "code_qualification_obs": 16, "libelle_qualification_obs": "Non qualifi\u00e9e", "continuite_obs_hydro": true, "longitude": 1.653886617, "latitude": 45.168892657}, {"code_site": "P3840101", "code_station": "P384010101", "grandeur_hydro": "Q", "date_debut_serie": "2024-09-18T00:00:01Z", "date_fin_serie": "2024-09-18T10:25:00Z", "statut_serie": 4, "code_systeme_alti_serie": 31, "date_obs": "2024-09-18T10:25:00Z", "resultat_obs": 340.0, "code_methode_obs": 12, "libelle_methode_obs": "Interpolation", "code_qualification_obs": 16, "libelle_qualification_obs": "Non qualifi\u00e9e", "continuite_obs_hydro": true, "longitude": 1.653886617, "latitude": 45.168892657}, {"code_site": "P3840101", "code_station": null, "grandeur_hydro": "Q", "date_debut_serie": "2024-09-18T00:00:01Z", "date_fin_serie": "2024-09-18T10:25:00Z", "statut_serie": 4, "code_systeme_alti_serie": 31, "date_obs": "2024-09-18T10:25:00Z", "resultat_obs": 340.0, "code_methode_obs": 12, "libelle_methode_obs": "Interpolation", "code_qualification_obs": 16, "libelle_qualification_obs": "Non qualifi\u00e9e", "continuite_obs_hydro": true, "longitude": 1.653886617, "latitude": 45.168892657}, {"code_site": "P5550010", "code_station": "P555001001", "grandeur_hydro": "H", "date_debut_serie": "2024-09-18T00:00:01Z", "date_fin_serie": "2024-09-18T10:25:00Z", "statut_serie": 4, "code_systeme_alti_serie": 31, "date_obs": "2024-09-18T10:25:00Z", "resultat_obs": 657.0, "code_methode_obs": 0, "libelle_methode_obs": "Mesure", "code_qualification_obs": 16, "libelle_qualification_obs": "Non qualifi\u00e9e", "continuite_obs_hydro": true, "longitude": 0.078035443, "latitude": 44.82123349}, {"code_site": "P5550010", "code_station": "P555001001", "grandeur_hydro": "Q", "date_debut_serie": "2024-09-18T00:00:01Z", "date_fin_serie": "2024-09-18T10:25:00Z", "statut_serie": 4, "code_systeme_alti_serie": 31, "date_obs": "2024-09-18T10:25:00Z", "resultat_obs": 103000.0, "code_methode_obs": 12, "libelle_methode_obs": "Interpolation", "code_qualification_obs": 16, "libelle_qualification_obs": "Non qualifi\u00e9e", "continuite_obs_hydro": true, "longitude": 0.078035443, "latitude": 44.82123349}, {"code_site": "P5550010", "code_station": null, "grandeur_hydro": "Q", "date_debut_serie": "2024-09-18T00:00:01Z", "date_fin_serie": "2024-09-18T10:25:00Z", "statut_serie": 4, "code_systeme_alti_serie": 31, "date_obs": "2024-09-18T10:25:00Z", "resultat_obs": 103000.0, "code_methode_obs": 12, "libelle_methode_obs": "Interpolation", "code_qualification_obs": 16, "libelle_qualification_obs": "Non qualifi\u00e9e", "continuite_obs_hydro": true, "longitude": 0.078035443, "latitude": 44.82123349}, {"code_site": "P6081510", "code_station": "P608151001", "grandeur_hydro": "H", "date_debut_serie": "2024-09-18T00:00:01Z", "date_fin_serie": "2024-09-18T10:25:00Z", "statut_serie": 4, "code_systeme_alti_serie": 31, "date_obs": "2024-09-18T10:25:00Z", "resultat_obs": 83.0, "code_methode_obs": 0, "libelle_methode_obs": "Mesure", "code_qualification_obs": 16, "libelle_qualification_obs": "Non qualifi\u00e9e", "continuite_obs_hydro": true, "longitude": 0.949463663, "latitude": 45.375493001}, {"code_site": "P6081510", "code_station": "P608151001", "grandeur_hydro": "Q", "date_debut_serie": "2024-09-18T00:00:01Z", "date_fin_serie": "2024-09-18T10:25:00Z", "statut_serie": 4, "code_systeme_alti_serie": 31, "date_obs": "2024-09-18T10:25:00Z", "resultat_obs": 1800.0, "code_methode_obs": 12, "libelle_methode_obs": "Interpolation", "code_qualification_obs": 16, "libelle_qualification_obs": "Non qualifi\u00e9e", "continuite_obs_hydro": true, "longitude": 0.949463663, "latitude": 45.375493001}, {"code_site": "P6081510", "code_station": null, "grandeur_hydro": "Q", "date_debut_serie": "2024-09-18T00:00:01Z", "date_fin_serie": "2024-09-18T10:25:00Z", "statut_serie": 4, "code_systeme_alti_serie": 31, "date_obs": "2024-09-18T10:25:00Z", "resultat_obs": 1800.0, "code_methode_obs": 12, "libelle_methode_obs": "Interpolation", "code_qualification_obs": 16, "libelle_qualification_obs": "Non qualifi\u00e9e", "continuite_obs_hydro": true, "longitude": 0.949399472, "latitude": 45.375500833}, {"code_site": "P8022520", "code_station": "P802252001", "grandeur_hydro": "H", "date_debut_serie": "2024-09-18T00:00:01Z", "date_fin_serie": "2024-09-18T10:25:00Z", "statut_serie": 4, "code_systeme_alti_serie": 31, "date_obs": "2024-09-18T10:25:00Z", "resultat_obs": -182.0, "code_methode_obs": 0, "libelle_methode_obs": "Mesure", "code_qualification_obs": 16, "libelle_qualification_obs": "Non qualifi\u00e9e", "continuite_obs_hydro": true, "longitude": 0.748124274, "latitude": 45.49209325}, {"code_site": "P8022520", "code_station": "P802252001", "grandeur_hydro": "Q", "date_debut_serie": "2024-09-18T00:00:01Z", "date_fin_serie": "2024-09-18T10:25:00Z", "statut_serie": 4, "code_systeme_alti_serie": 31, "date_obs": "2024-09-18T10:25:00Z", "resultat_obs": 727.0, "code_methode_obs": 12, "libelle_methode_obs": "Interpolation", "code_qualification_obs": 16, "libelle_qualification_obs": "Non qualifi\u00e9e", "continuite_obs_hydro": true, "longitude": 0.748124274, "latitude": 45.49209325}, {"code_site": "P8022520", "code_station": null, "grandeur_hydro": "Q", "date_debut_serie": "2024-09-18T00:00:01Z", "date_fin_serie": "2024-09-18T10:25:00Z", "statut_serie": 4, "code_systeme_alti_serie": 31, "date_obs": "2024-09-18T10:25:00Z", "resultat_obs": 727.0, "code_methode_obs": 12, "libelle_methode_obs": "Interpolation", "code_qualification_obs": 16, "libelle_qualification_obs": "Non qualifi\u00e9e", "continuite_obs_hydro": true, "longitude": 0.748124274, "latitude": 45.49209325}, {"code_site": "P8162510", "code_station": "P816251001", "grandeur_hydro": "H", "date_debut_serie": "2024-09-18T00:00:01Z", "date_fin_serie": "2024-09-18T10:25:00Z", "statut_serie": 4, "code_systeme_alti_serie": 31, "date_obs": "2024-09-18T10:25:00Z", "resultat_obs": 178.0, "code_methode_obs": 0, "libelle_methode_obs": "Mesure", "code_qualification_obs": 16, "libelle_qualification_obs": "Non qualifi\u00e9e", "continuite_obs_hydro": true, "longitude": 0.342336589, "latitude": 45.256247536}, {"code_site": "Q2663110", "code_station": "Q266311001", "grandeur_hydro": "H", "date_debut_serie": "2024-09-18T00:00:00Z", "date_fin_serie": "2024-09-18T10:25:00Z", "statut_serie": 4, "code_systeme_alti_serie": 31, "date_obs": "2024-09-18T10:25:00Z", "resultat_obs": -402.0, "code_methode_obs": 0, "libelle_methode_obs": "Mesure", "code_qualification_obs": 16, "libelle_qualification_obs": "Non qualifi\u00e9e", "continuite_obs_hydro": true, "longitude": -0.807511638, "latitude": 43.833023748}, {"code_site": "Q2663110", "code_station": "Q266311001", "grandeur_hydro": "Q", "date_debut_serie": "2024-09-18T00:00:00Z", "date_fin_serie": "2024-09-18T10:25:00Z", "statut_serie": 4, "code_systeme_alti_serie": 31, "date_obs": "2024-09-18T10:25:00Z", "resultat_obs": 12400.0, "code_methode_obs": 12, "libelle_methode_obs": "Interpolation", "code_qualification_obs": 16, "libelle_qualification_obs": "Non qualifi\u00e9e", "continuite_obs_hydro": true, "longitude": -0.807511638, "latitude": 43.833023748}, {"code_site": "Q2663110", "code_station": null, "grandeur_hydro": "Q", "date_debut_serie": "2024-09-18T00:00:00Z", "date_fin_serie": "2024-09-18T10:25:00Z", "statut_serie": 4, "code_systeme_alti_serie": 31, "date_obs": "2024-09-18T10:25:00Z", "resultat_obs": 12400.0, "code_methode_obs": 12, "libelle_methode_obs": "Interpolation", "code_qualification_obs": 16, "libelle_qualification_obs": "Non qualifi\u00e9e", "continuite_obs_hydro": true, "longitude": -0.806652741, "latitude": 43.832648321}, {"code_site": "V3714020", "code_station": "V371402001", "grandeur_hydro": "H", "date_debut_serie": "2024-09-18T00:00:00Z", "date_fin_serie": "2024-09-18T10:25:00Z", "statut_serie": 4, "code_systeme_alti_serie": 31, "date_obs": "2024-09-18T10:25:00Z", "resultat_obs": -162.0, "code_methode_obs": 0, "libelle_methode_obs": "Mesure", "code_qualification_obs": 16, "libelle_qualification_obs": "Non qualifi\u00e9e", "continuite_obs_hydro": true, "longitude": 4.577808105, "latitude": 44.987841566}, {"code_site": "V3714020", "code_station": "V371402001", "grandeur_hydro": "Q", "date_debut_serie": "2024-09-18T00:00:00Z", "date_fin_serie": "2024-09-18T10:25:00Z", "statut_serie": 4, "code_systeme_alti_serie": 31, "date_obs": "2024-09-18T10:25:00Z", "resultat_obs": 766.0, "code_methode_obs": 12, "libelle_methode_obs": "Interpolation", "code_qualification_obs": 16, "libelle_qualification_obs": "Non qualifi\u00e9e", "continuite_obs_hydro": true, "longitude": 4.577808105, "latitude": 44.987841566}, {"code_site": "V3714020", "code_station": null, "grandeur_hydro": "Q", "date_debut_serie": "2024-09-18T00:00:00Z", "date_fin_serie": "2024-09-18T10:25:00Z", "statut_serie": 4, "code_systeme_alti_serie": 31, "date_obs": "2024-09-18T10:25:00Z", "resultat_obs": 766.0, "code_methode_obs": 12, "libelle_methode_obs": "Interpolation", "code_qualification_obs": 16, "libelle_qualification_obs": "Non qualifi\u00e9e", "continuite_obs_hydro": true, "longitude": 4.578498439, "latitude": 44.987120338}, {"code_site": "V4124010", "code_station": "V412401001", "grandeur_hydro": "H", "date_debut_serie": "2024-09-18T00:10:00Z", "date_fin_serie": "2024-09-18T10:25:00Z", "statut_serie": 4, "code_systeme_alti_serie": 31, "date_obs": "2024-09-18T10:25:00Z", "resultat_obs": 146.0, "code_methode_obs": 0, "libelle_methode_obs": "Mesure", "code_qualification_obs": 16, "libelle_qualification_obs": "Non qualifi\u00e9e", "continuite_obs_hydro": true, "longitude": 4.427979681, "latitude": 44.912754844}, {"code_site": "V4154010", "code_station": "V415401001", "grandeur_hydro": "H", "date_debut_serie": "2024-09-18T00:00:00Z", "date_fin_serie": "2024-09-18T10:25:00Z", "statut_serie": 4, "code_systeme_alti_serie": 31, "date_obs": "2024-09-18T10:25:00Z", "resultat_obs": 162.0, "code_methode_obs": 0, "libelle_methode_obs": "Mesure", "code_qualification_obs": 16, "libelle_qualification_obs": "Non qualifi\u00e9e", "continuite_obs_hydro": true, "longitude": 4.615584556, "latitude": 44.811280632}, {"code_site": "V5014030", "code_station": "V501403001", "grandeur_hydro": "H", "date_debut_serie": "2024-09-18T00:00:00Z", "date_fin_serie": "2024-09-18T10:25:00Z", "statut_serie": 4, "code_systeme_alti_serie": 31, "date_obs": "2024-09-18T10:25:00Z", "resultat_obs": 14.0, "code_methode_obs": 0, "libelle_methode_obs": "Mesure", "code_qualification_obs": 16, "libelle_qualification_obs": "Non qualifi\u00e9e", "continuite_obs_hydro": true, "longitude": 4.395445211, "latitude": 44.626798269}, {"code_site": "V5014030", "code_station": "V501403001", "grandeur_hydro": "Q", "date_debut_serie": "2024-09-18T00:00:00Z", "date_fin_serie": "2024-09-18T10:25:00Z", "statut_serie": 4, "code_systeme_alti_serie": 31, "date_obs": "2024-09-18T10:25:00Z", "resultat_obs": 4180.0, "code_methode_obs": 12, "libelle_methode_obs": "Interpolation", "code_qualification_obs": 16, "libelle_qualification_obs": "Non qualifi\u00e9e", "continuite_obs_hydro": true, "longitude": 4.395445211, "latitude": 44.626798269}, {"code_site": "V5014030", "code_station": null, "grandeur_hydro": "Q", "date_debut_serie": "2024-09-18T00:00:00Z", "date_fin_serie": "2024-09-18T10:25:00Z", "statut_serie": 4, "code_systeme_alti_serie": 31, "date_obs": "2024-09-18T10:25:00Z", "resultat_obs": 4180.0, "code_methode_obs": 12, "libelle_methode_obs": "Interpolation", "code_qualification_obs": 16, "libelle_qualification_obs": "Non qualifi\u00e9e", "continuite_obs_hydro": true, "longitude": 4.395445211, "latitude": 44.626798269}, {"code_site": "V5035020", "code_station": "V503502001", "grandeur_hydro": "H", "date_debut_serie": "2024-09-18T00:00:00Z", "date_fin_serie": "2024-09-18T10:25:00Z", "statut_serie": 4, "code_systeme_alti_serie": 31, "date_obs": "2024-09-18T10:25:00Z", "resultat_obs": 19.0, "code_methode_obs": 0, "libelle_methode_obs": "Mesure", "code_qualification_obs": 16, "libelle_qualification_obs": "Non qualifi\u00e9e", "continuite_obs_hydro": true, "longitude": 4.251388748, "latitude": 44.481612602}, {"code_site": "V5035020", "code_station": "V503502001", "grandeur_hydro": "Q", "date_debut_serie": "2024-09-18T00:00:00Z", "date_fin_serie": "2024-09-18T10:25:00Z", "statut_serie": 4, "code_systeme_alti_serie": 31, "date_obs": "2024-09-18T10:25:00Z", "resultat_obs": 908.0, "code_methode_obs": 12, "libelle_methode_obs": "Interpolation", "code_qualification_obs": 12, "libelle_qualification_obs": "Douteuse", "continuite_obs_hydro": true, "longitude": 4.251388748, "latitude": 44.481612602}, {"code_site": "V5035020", "code_station": null, "grandeur_hydro": "Q", "date_debut_serie": "2024-09-18T00:00:00Z", "date_fin_serie": "2024-09-18T10:25:00Z", "statut_serie": 4, "code_systeme_alti_serie": 31, "date_obs": "2024-09-18T10:25:00Z", "resultat_obs": 908.0, "code_methode_obs": 12, "libelle_methode_obs": "Interpolation", "code_qualification_obs": 12, "libelle_qualification_obs": "Douteuse", "continuite_obs_hydro": true, "longitude": 4.251388748, "latitude": 44.481612602}, {"code_site": "V5131010", "code_station": "V513101001", "grandeur_hydro": "H", "date_debut_serie": "2024-09-18T00:00:00Z", "date_fin_serie": "2024-09-18T10:25:00Z", "statut_serie": 4, "code_systeme_alti_serie": 31, "date_obs": "2024-09-18T10:25:00Z", "resultat_obs": 1650.0, "code_methode_obs": 0, "libelle_methode_obs": "Mesure", "code_qualification_obs": 16, "libelle_qualification_obs": "Non qualifi\u00e9e", "continuite_obs_hydro": true, "longitude": 4.649295748, "latitude": 44.260350149}, {"code_site": "V5131010", "code_station": "V513101001", "grandeur_hydro": "Q", "date_debut_serie": "2024-09-18T00:00:00Z", "date_fin_serie": "2024-09-18T10:25:00Z", "statut_serie": 4, "code_systeme_alti_serie": 31, "date_obs": "2024-09-18T10:25:00Z", "resultat_obs": 92100.0, "code_methode_obs": 12, "libelle_methode_obs": "Interpolation", "code_qualification_obs": 16, "libelle_qualification_obs": "Non qualifi\u00e9e", "continuite_obs_hydro": true, "longitude": 4.649295748, "latitude": 44.260350149}, {"code_site": "V5131010", "code_station": null, "grandeur_hydro": "Q", "date_debut_serie": "2024-09-18T00:00:00Z", "date_fin_serie": "2024-09-18T10:25:00Z", "statut_serie": 4, "code_systeme_alti_serie": 31, "date_obs": "2024-09-18T10:25:00Z", "resultat_obs": 92100.0, "code_methode_obs": 12, "libelle_methode_obs": "Interpolation", "code_qualification_obs": 16, "libelle_qualification_obs": "Non qualifi\u00e9e", "continuite_obs_hydro": true, "longitude": 4.649054349, "latitude": 44.260224904}, {"code_site": "V5424010", "code_station": "V542401001", "grandeur_hydro": "H", "date_debut_serie": "2024-09-18T00:00:00Z", "date_fin_serie": "2024-09-18T10:25:00Z", "statut_serie": 4, "code_systeme_alti_serie": 31, "date_obs": "2024-09-18T10:25:00Z", "resultat_obs": 154.0, "code_methode_obs": 0, "libelle_methode_obs": "Mesure", "code_qualification_obs": 16, "libelle_qualification_obs": "Non qualifi\u00e9e", "continuite_obs_hydro": true, "longitude": 4.093307875, "latitude": 44.296037026}, {"code_site": "V5424010", "code_station": "V542401001", "grandeur_hydro": "Q", "date_debut_serie": "2024-09-18T00:00:00Z", "date_fin_serie": "2024-09-18T10:25:00Z", "statut_serie": 4, "code_systeme_alti_serie": 31, "date_obs": "2024-09-18T10:25:00Z", "resultat_obs": 426.0, "code_methode_obs": 12, "libelle_methode_obs": "Interpolation", "code_qualification_obs": 12, "libelle_qualification_obs": "Douteuse", "continuite_obs_hydro": true, "longitude": 4.093307875, "latitude": 44.296037026}, {"code_site": "V5424010", "code_station": null, "grandeur_hydro": "Q", "date_debut_serie": "2024-09-18T00:00:00Z", "date_fin_serie": "2024-09-18T10:25:00Z", "statut_serie": 4, "code_systeme_alti_serie": 31, "date_obs": "2024-09-18T10:25:00Z", "resultat_obs": 426.0, "code_methode_obs": 12, "libelle_methode_obs": "Interpolation", "code_qualification_obs": 12, "libelle_qualification_obs": "Douteuse", "continuite_obs_hydro": true, "longitude": 4.093280531, "latitude": 44.29613155}, {"code_site": "V5464015", "code_station": "V546401501", "grandeur_hydro": "H", "date_debut_serie": "2024-09-18T00:00:00Z", "date_fin_serie": "2024-09-18T10:25:00Z", "statut_serie": 4, "code_systeme_alti_serie": 31, "date_obs": "2024-09-18T10:25:00Z", "resultat_obs": 291.0, "code_methode_obs": 0, "libelle_methode_obs": "Mesure", "code_qualification_obs": 16, "libelle_qualification_obs": "Non qualifi\u00e9e", "continuite_obs_hydro": true, "longitude": 4.430450654, "latitude": 44.264405558}, {"code_site": "V5464015", "code_station": "V546401501", "grandeur_hydro": "Q", "date_debut_serie": "2024-09-18T00:00:00Z", "date_fin_serie": "2024-09-18T10:25:00Z", "statut_serie": 4, "code_systeme_alti_serie": 31, "date_obs": "2024-09-18T10:25:00Z", "resultat_obs": 1250.0, "code_methode_obs": 12, "libelle_methode_obs": "Interpolation", "code_qualification_obs": 16, "libelle_qualification_obs": "Non qualifi\u00e9e", "continuite_obs_hydro": true, "longitude": 4.430450654, "latitude": 44.264405558}, {"code_site": "V5464015", "code_station": null, "grandeur_hydro": "Q", "date_debut_serie": "2024-09-18T00:00:00Z", "date_fin_serie": "2024-09-18T10:25:00Z", "statut_serie": 4, "code_systeme_alti_serie": 31, "date_obs": "2024-09-18T10:25:00Z", "resultat_obs": 1250.0, "code_methode_obs": 12, "libelle_methode_obs": "Interpolation", "code_qualification_obs": 16, "libelle_qualification_obs": "Non qualifi\u00e9e", "continuite_obs_hydro": true, "longitude": 4.43051271, "latitude": 44.264458887}, {"code_site": "V5474015", "code_station": "V547401501", "grandeur_hydro": "H", "date_debut_serie": "2024-09-18T00:00:00Z", "date_fin_serie": "2024-09-18T10:25:00Z", "statut_serie": 4, "code_systeme_alti_serie": 31, "date_obs": "2024-09-18T10:25:00Z", "resultat_obs": 417.0, "code_methode_obs": 0, "libelle_methode_obs": "Mesure", "code_qualification_obs": 16, "libelle_qualification_obs": "Non qualifi\u00e9e", "continuite_obs_hydro": true, "longitude": 4.620008053, "latitude": 44.170230509}, {"code_site": "V5474015", "code_station": "V547401501", "grandeur_hydro": "Q", "date_debut_serie": "2024-09-18T00:00:00Z", "date_fin_serie": "2024-09-18T10:25:00Z", "statut_serie": 4, "code_systeme_alti_serie": 31, "date_obs": "2024-09-18T10:25:00Z", "resultat_obs": 1610.0, "code_methode_obs": 12, "libelle_methode_obs": "Interpolation", "code_qualification_obs": 16, "libelle_qualification_obs": "Non qualifi\u00e9e", "continuite_obs_hydro": true, "longitude": 4.620008053, "latitude": 44.170230509}, {"code_site": "V5474015", "code_station": null, "grandeur_hydro": "Q", "date_debut_serie": "2024-09-18T00:00:00Z", "date_fin_serie": "2024-09-18T10:25:00Z", "statut_serie": 4, "code_systeme_alti_serie": 31, "date_obs": "2024-09-18T10:25:00Z", "resultat_obs": 1610.0, "code_methode_obs": 12, "libelle_methode_obs": "Interpolation", "code_qualification_obs": 16, "libelle_qualification_obs": "Non qualifi\u00e9e", "continuite_obs_hydro": true, "longitude": 4.620347871, "latitude": 44.170144655}, {"code_site": "V6042010", "code_station": "V604201001", "grandeur_hydro": "H", "date_debut_serie": "2024-09-18T00:00:00Z", "date_fin_serie": "2024-09-18T10:25:00Z", "statut_serie": 4, "code_systeme_alti_serie": 31, "date_obs": "2024-09-18T10:25:00Z", "resultat_obs": 62.0, "code_methode_obs": 0, "libelle_methode_obs": "Mesure", "code_qualification_obs": 16, "libelle_qualification_obs": "Non qualifi\u00e9e", "continuite_obs_hydro": true, "longitude": 5.136699284, "latitude": 44.229067748}, {"code_site": "V6051010", "code_station": "V605101001", "grandeur_hydro": "H", "date_debut_serie": "2024-09-18T00:00:00Z", "date_fin_serie": "2024-09-18T10:25:00Z", "statut_serie": 4, "code_systeme_alti_serie": 31, "date_obs": "2024-09-18T10:25:00Z", "resultat_obs": 826.0, "code_methode_obs": 0, "libelle_methode_obs": "Mesure", "code_qualification_obs": 16, "libelle_qualification_obs": "Non qualifi\u00e9e", "continuite_obs_hydro": true, "longitude": 5.012281043, "latitude": 44.240872729}, {"code_site": "V6051010", "code_station": "V605101001", "grandeur_hydro": "Q", "date_debut_serie": "2024-09-18T00:00:00Z", "date_fin_serie": "2024-09-18T10:25:00Z", "statut_serie": 4, "code_systeme_alti_serie": 31, "date_obs": "2024-09-18T10:25:00Z", "resultat_obs": 3600.0, "code_methode_obs": 12, "libelle_methode_obs": "Interpolation", "code_qualification_obs": 16, "libelle_qualification_obs": "Non qualifi\u00e9e", "continuite_obs_hydro": true, "longitude": 5.012281043, "latitude": 44.240872729}, {"code_site": "V6051010", "code_station": null, "grandeur_hydro": "Q", "date_debut_serie": "2024-09-18T00:00:00Z", "date_fin_serie": "2024-09-18T10:25:00Z", "statut_serie": 4, "code_systeme_alti_serie": 31, "date_obs": "2024-09-18T10:25:00Z", "resultat_obs": 3600.0, "code_methode_obs": 12, "libelle_methode_obs": "Interpolation", "code_qualification_obs": 16, "libelle_qualification_obs": "Non qualifi\u00e9e", "continuite_obs_hydro": true, "longitude": 5.012281043, "latitude": 44.240872729}, {"code_site": "V6202010", "code_station": "V620201001", "grandeur_hydro": "H", "date_debut_serie": "2024-09-18T00:00:00Z", "date_fin_serie": "2024-09-18T10:25:00Z", "statut_serie": 4, "code_systeme_alti_serie": 31, "date_obs": "2024-09-18T10:25:00Z", "resultat_obs": 659.0, "code_methode_obs": 0, "libelle_methode_obs": "Mesure", "code_qualification_obs": 16, "libelle_qualification_obs": "Non qualifi\u00e9e", "continuite_obs_hydro": true, "longitude": 4.895777409, "latitude": 44.039545403}, {"code_site": "V6202010", "code_station": "V620201001", "grandeur_hydro": "Q", "date_debut_serie": "2024-09-18T00:00:00Z", "date_fin_serie": "2024-09-18T10:25:00Z", "statut_serie": 4, "code_systeme_alti_serie": 31, "date_obs": "2024-09-18T10:25:00Z", "resultat_obs": 4130.0, "code_methode_obs": 12, "libelle_methode_obs": "Interpolation", "code_qualification_obs": 16, "libelle_qualification_obs": "Non qualifi\u00e9e", "continuite_obs_hydro": true, "longitude": 4.895777409, "latitude": 44.039545403}, {"code_site": "V6202010", "code_station": null, "grandeur_hydro": "Q", "date_debut_serie": "2024-09-18T00:00:00Z", "date_fin_serie": "2024-09-18T10:25:00Z", "statut_serie": 4, "code_systeme_alti_serie": 31, "date_obs": "2024-09-18T10:25:00Z", "resultat_obs": 4130.0, "code_methode_obs": 12, "libelle_methode_obs": "Interpolation", "code_qualification_obs": 16, "libelle_qualification_obs": "Non qualifi\u00e9e", "continuite_obs_hydro": true, "longitude": 4.895777409, "latitude": 44.039545403}, {"code_site": "V6215010", "code_station": "V621501001", "grandeur_hydro": "H", "date_debut_serie": "2024-09-18T00:00:00Z", "date_fin_serie": "2024-09-18T10:25:00Z", "statut_serie": 4, "code_systeme_alti_serie": 31, "date_obs": "2024-09-18T10:25:00Z", "resultat_obs": 3335.0, "code_methode_obs": 0, "libelle_methode_obs": "Mesure", "code_qualification_obs": 16, "libelle_qualification_obs": "Non qualifi\u00e9e", "continuite_obs_hydro": true, "longitude": 4.799149386, "latitude": 43.951549084}, {"code_site": "V7124015", "code_station": "V712401501", "grandeur_hydro": "H", "date_debut_serie": "2024-09-18T08:30:00Z", "date_fin_serie": "2024-09-18T10:25:00Z", "statut_serie": 4, "code_systeme_alti_serie": 31, "date_obs": "2024-09-18T10:25:00Z", "resultat_obs": 214.0, "code_methode_obs": 0, "libelle_methode_obs": "Mesure", "code_qualification_obs": 16, "libelle_qualification_obs": "Non qualifi\u00e9e", "continuite_obs_hydro": true, "longitude": 3.909514565, "latitude": 44.125874228}, {"code_site": "V7124015", "code_station": "V712401501", "grandeur_hydro": "Q", "date_debut_serie": "2024-09-18T08:30:00Z", "date_fin_serie": "2024-09-18T10:25:00Z", "statut_serie": 4, "code_systeme_alti_serie": 31, "date_obs": "2024-09-18T10:25:00Z", "resultat_obs": 267.0, "code_methode_obs": 12, "libelle_methode_obs": "Interpolation", "code_qualification_obs": 16, "libelle_qualification_obs": "Non qualifi\u00e9e", "continuite_obs_hydro": true, "longitude": 3.909514565, "latitude": 44.125874228}, {"code_site": "V7124015", "code_station": null, "grandeur_hydro": "Q", "date_debut_serie": "2024-09-18T08:30:00Z", "date_fin_serie": "2024-09-18T10:25:00Z", "statut_serie": 4, "code_systeme_alti_serie": 31, "date_obs": "2024-09-18T10:25:00Z", "resultat_obs": 267.0, "code_methode_obs": 12, "libelle_methode_obs": "Interpolation", "code_qualification_obs": 16, "libelle_qualification_obs": "Non qualifi\u00e9e", "continuite_obs_hydro": true, "longitude": 3.91016881, "latitude": 44.124718141}, {"code_site": "V7144010", "code_station": "V714401001", "grandeur_hydro": "H", "date_debut_serie": "2024-09-18T00:00:00Z", "date_fin_serie": "2024-09-18T10:25:00Z", "statut_serie": 4, "code_systeme_alti_serie": 31, "date_obs": "2024-09-18T10:25:00Z", "resultat_obs": 117.0, "code_methode_obs": 0, "libelle_methode_obs": "Mesure", "code_qualification_obs": 16, "libelle_qualification_obs": "Non qualifi\u00e9e", "continuite_obs_hydro": true, "longitude": 3.984925912, "latitude": 44.060102126}, {"code_site": "V7155010", "code_station": "V715501001", "grandeur_hydro": "H", "date_debut_serie": "2024-09-18T00:00:00Z", "date_fin_serie": "2024-09-18T10:25:00Z", "statut_serie": 4, "code_systeme_alti_serie": 31, "date_obs": "2024-09-18T10:25:00Z", "resultat_obs": 381.0, "code_methode_obs": 0, "libelle_methode_obs": "Mesure", "code_qualification_obs": 16, "libelle_qualification_obs": "Non qualifi\u00e9e", "continuite_obs_hydro": true, "longitude": 4.078850426, "latitude": 44.120354719}, {"code_site": "V7155010", "code_station": "V715501001", "grandeur_hydro": "Q", "date_debut_serie": "2024-09-18T00:00:00Z", "date_fin_serie": "2024-09-18T10:25:00Z", "statut_serie": 4, "code_systeme_alti_serie": 31, "date_obs": "2024-09-18T10:25:00Z", "resultat_obs": 825.0, "code_methode_obs": 12, "libelle_methode_obs": "Interpolation", "code_qualification_obs": 16, "libelle_qualification_obs": "Non qualifi\u00e9e", "continuite_obs_hydro": true, "longitude": 4.078850426, "latitude": 44.120354719}, {"code_site": "V7155010", "code_station": null, "grandeur_hydro": "Q", "date_debut_serie": "2024-09-18T00:00:00Z", "date_fin_serie": "2024-09-18T10:25:00Z", "statut_serie": 4, "code_systeme_alti_serie": 31, "date_obs": "2024-09-18T10:25:00Z", "resultat_obs": 825.0, "code_methode_obs": 12, "libelle_methode_obs": "Interpolation", "code_qualification_obs": 16, "libelle_qualification_obs": "Non qualifi\u00e9e", "continuite_obs_hydro": true, "longitude": 4.078929551, "latitude": 44.120376252}, {"code_site": "V7155035", "code_station": "V715503501", "grandeur_hydro": "H", "date_debut_serie": "2024-09-18T00:00:00Z", "date_fin_serie": "2024-09-18T10:25:00Z", "statut_serie": 4, "code_systeme_alti_serie": 31, "date_obs": "2024-09-18T10:25:00Z", "resultat_obs": 242020.0, "code_methode_obs": 0, "libelle_methode_obs": "Mesure", "code_qualification_obs": 16, "libelle_qualification_obs": "Non qualifi\u00e9e", "continuite_obs_hydro": true, "longitude": 3.980965035, "latitude": 44.242283002}, {"code_site": "V7155035", "code_station": "V715503501", "grandeur_hydro": "Q", "date_debut_serie": "2024-09-18T00:00:00Z", "date_fin_serie": "2024-09-18T10:25:00Z", "statut_serie": 4, "code_systeme_alti_serie": 31, "date_obs": "2024-09-18T10:25:00Z", "resultat_obs": 202.0, "code_methode_obs": 12, "libelle_methode_obs": "Interpolation", "code_qualification_obs": 16, "libelle_qualification_obs": "Non qualifi\u00e9e", "continuite_obs_hydro": true, "longitude": 3.980965035, "latitude": 44.242283002}, {"code_site": "V7155035", "code_station": null, "grandeur_hydro": "Q", "date_debut_serie": "2024-09-18T00:00:00Z", "date_fin_serie": "2024-09-18T10:25:00Z", "statut_serie": 4, "code_systeme_alti_serie": 31, "date_obs": "2024-09-18T10:25:00Z", "resultat_obs": 202.0, "code_methode_obs": 12, "libelle_methode_obs": "Interpolation", "code_qualification_obs": 16, "libelle_qualification_obs": "Non qualifi\u00e9e", "continuite_obs_hydro": true, "longitude": 3.980506619, "latitude": 44.242323629}, {"code_site": "V7164015", "code_station": "V716401501", "grandeur_hydro": "H", "date_debut_serie": "2024-09-18T00:00:00Z", "date_fin_serie": "2024-09-18T10:25:00Z", "statut_serie": 4, "code_systeme_alti_serie": 31, "date_obs": "2024-09-18T10:25:00Z", "resultat_obs": 424.0, "code_methode_obs": 0, "libelle_methode_obs": "Mesure", "code_qualification_obs": 16, "libelle_qualification_obs": "Non qualifi\u00e9e", "continuite_obs_hydro": true, "longitude": 4.155089928, "latitude": 44.015843166}, {"code_site": "V7164015", "code_station": "V716401501", "grandeur_hydro": "Q", "date_debut_serie": "2024-09-18T00:00:00Z", "date_fin_serie": "2024-09-18T10:25:00Z", "statut_serie": 4, "code_systeme_alti_serie": 31, "date_obs": "2024-09-18T10:25:00Z", "resultat_obs": 1970.0, "code_methode_obs": 12, "libelle_methode_obs": "Interpolation", "code_qualification_obs": 16, "libelle_qualification_obs": "Non qualifi\u00e9e", "continuite_obs_hydro": true, "longitude": 4.155089928, "latitude": 44.015843166}, {"code_site": "V7164015", "code_station": null, "grandeur_hydro": "Q", "date_debut_serie": "2024-09-18T00:00:00Z", "date_fin_serie": "2024-09-18T10:25:00Z", "statut_serie": 4, "code_systeme_alti_serie": 31, "date_obs": "2024-09-18T10:25:00Z", "resultat_obs": 1970.0, "code_methode_obs": 12, "libelle_methode_obs": "Interpolation", "code_qualification_obs": 16, "libelle_qualification_obs": "Non qualifi\u00e9e", "continuite_obs_hydro": true, "longitude": 4.154293321, "latitude": 44.015889198}, {"code_site": "V7184015", "code_station": "V718401501", "grandeur_hydro": "H", "date_debut_serie": "2024-09-18T00:00:00Z", "date_fin_serie": "2024-09-18T10:25:00Z", "statut_serie": 4, "code_systeme_alti_serie": 31, "date_obs": "2024-09-18T10:25:00Z", "resultat_obs": -682.0, "code_methode_obs": 0, "libelle_methode_obs": "Mesure", "code_qualification_obs": 16, "libelle_qualification_obs": "Non qualifi\u00e9e", "continuite_obs_hydro": true, "longitude": 4.32027411, "latitude": 43.931512241}, {"code_site": "V7194010", "code_station": "V719401001", "grandeur_hydro": "H", "date_debut_serie": "2024-09-18T00:00:00Z", "date_fin_serie": "2024-09-18T10:25:00Z", "statut_serie": 4, "code_systeme_alti_serie": 31, "date_obs": "2024-09-18T10:25:00Z", "resultat_obs": -1694.0, "code_methode_obs": 0, "libelle_methode_obs": "Mesure", "code_qualification_obs": 16, "libelle_qualification_obs": "Non qualifi\u00e9e", "continuite_obs_hydro": true, "longitude": 4.556605005, "latitude": 43.937290465}, {"code_site": "V7194010", "code_station": "V719401001", "grandeur_hydro": "Q", "date_debut_serie": "2024-09-18T00:00:00Z", "date_fin_serie": "2024-09-18T10:25:00Z", "statut_serie": 4, "code_systeme_alti_serie": 31, "date_obs": "2024-09-18T10:25:00Z", "resultat_obs": 7490.0, "code_methode_obs": 12, "libelle_methode_obs": "Interpolation", "code_qualification_obs": 12, "libelle_qualification_obs": "Douteuse", "continuite_obs_hydro": true, "longitude": 4.556605005, "latitude": 43.937290465}, {"code_site": "V7200005", "code_station": "V720000501", "grandeur_hydro": "H", "date_debut_serie": "2024-09-18T00:00:00Z", "date_fin_serie": "2024-09-18T10:25:00Z", "statut_serie": 4, "code_systeme_alti_serie": 31, "date_obs": "2024-09-18T10:25:00Z", "resultat_obs": 1433.0, "code_methode_obs": 0, "libelle_methode_obs": "Mesure", "code_qualification_obs": 16, "libelle_qualification_obs": "Non qualifi\u00e9e", "continuite_obs_hydro": true, "longitude": 4.649077876, "latitude": 43.804384672}, {"code_site": "W0500006", "code_station": "W050000602", "grandeur_hydro": "H", "date_debut_serie": "2024-09-18T09:40:00Z", "date_fin_serie": "2024-09-18T10:25:00Z", "statut_serie": 4, "code_systeme_alti_serie": 31, "date_obs": "2024-09-18T10:25:00Z", "resultat_obs": 43.0, "code_methode_obs": 0, "libelle_methode_obs": "Mesure", "code_qualification_obs": 16, "libelle_qualification_obs": "Non qualifi\u00e9e", "continuite_obs_hydro": true, "longitude": 6.317940595, "latitude": 45.631687235}, {"code_site": "X3020010", "code_station": "X302001001", "grandeur_hydro": "H", "date_debut_serie": "2024-09-18T00:00:00Z", "date_fin_serie": "2024-09-18T10:25:00Z", "statut_serie": 4, "code_systeme_alti_serie": 31, "date_obs": "2024-09-18T10:25:00Z", "resultat_obs": 418.0, "code_methode_obs": 0, "libelle_methode_obs": "Mesure", "code_qualification_obs": 16, "libelle_qualification_obs": "Non qualifi\u00e9e", "continuite_obs_hydro": true, "longitude": 5.494158239, "latitude": 43.66595002}, {"code_site": "X3020010", "code_station": "X302001001", "grandeur_hydro": "Q", "date_debut_serie": "2024-09-18T00:00:00Z", "date_fin_serie": "2024-09-18T10:25:00Z", "statut_serie": 4, "code_systeme_alti_serie": 31, "date_obs": "2024-09-18T10:25:00Z", "resultat_obs": 10800.0, "code_methode_obs": 12, "libelle_methode_obs": "Interpolation", "code_qualification_obs": 16, "libelle_qualification_obs": "Non qualifi\u00e9e", "continuite_obs_hydro": true, "longitude": 5.494158239, "latitude": 43.66595002}, {"code_site": "X3020010", "code_station": null, "grandeur_hydro": "Q", "date_debut_serie": "2024-09-18T00:00:00Z", "date_fin_serie": "2024-09-18T10:25:00Z", "statut_serie": 4, "code_systeme_alti_serie": 31, "date_obs": "2024-09-18T10:25:00Z", "resultat_obs": 10800.0, "code_methode_obs": 12, "libelle_methode_obs": "Interpolation", "code_qualification_obs": 16, "libelle_qualification_obs": "Non qualifi\u00e9e", "continuite_obs_hydro": true, "longitude": 5.494158239, "latitude": 43.66595002}, {"code_site": "X3310010", "code_station": "X331001001", "grandeur_hydro": "H", "date_debut_serie": "2024-09-18T00:00:00Z", "date_fin_serie": "2024-09-18T10:25:00Z", "statut_serie": 4, "code_systeme_alti_serie": 31, "date_obs": "2024-09-18T10:25:00Z", "resultat_obs": 451.0, "code_methode_obs": 0, "libelle_methode_obs": "Mesure", "code_qualification_obs": 16, "libelle_qualification_obs": "Non qualifi\u00e9e", "continuite_obs_hydro": true, "longitude": 5.032432216, "latitude": 43.82748691}, {"code_site": "X3310010", "code_station": "X331001001", "grandeur_hydro": "Q", "date_debut_serie": "2024-09-18T00:00:00Z", "date_fin_serie": "2024-09-18T10:25:00Z", "statut_serie": 4, "code_systeme_alti_serie": 31, "date_obs": "2024-09-18T10:25:00Z", "resultat_obs": 10600.0, "code_methode_obs": 12, "libelle_methode_obs": "Interpolation", "code_qualification_obs": 12, "libelle_qualification_obs": "Douteuse", "continuite_obs_hydro": true, "longitude": 5.032432216, "latitude": 43.82748691}, {"code_site": "X3310010", "code_station": null, "grandeur_hydro": "Q", "date_debut_serie": "2024-09-18T00:00:00Z", "date_fin_serie": "2024-09-18T10:25:00Z", "statut_serie": 4, "code_systeme_alti_serie": 31, "date_obs": "2024-09-18T10:25:00Z", "resultat_obs": 10600.0, "code_methode_obs": 12, "libelle_methode_obs": "Interpolation", "code_qualification_obs": 12, "libelle_qualification_obs": "Douteuse", "continuite_obs_hydro": true, "longitude": 5.032432216, "latitude": 43.82748691}, {"code_site": "X3310020", "code_station": "X331002001", "grandeur_hydro": "H", "date_debut_serie": "2024-09-18T00:00:00Z", "date_fin_serie": "2024-09-18T10:25:00Z", "statut_serie": 4, "code_systeme_alti_serie": 31, "date_obs": "2024-09-18T10:25:00Z", "resultat_obs": 367.0, "code_methode_obs": 0, "libelle_methode_obs": "Mesure", "code_qualification_obs": 16, "libelle_qualification_obs": "Non qualifi\u00e9e", "continuite_obs_hydro": true, "longitude": 5.173713896, "latitude": 43.737373397}, {"code_site": "X3414010", "code_station": "X341401001", "grandeur_hydro": "H", "date_debut_serie": "2024-09-18T00:00:00Z", "date_fin_serie": "2024-09-18T10:25:00Z", "statut_serie": 4, "code_systeme_alti_serie": 31, "date_obs": "2024-09-18T10:25:00Z", "resultat_obs": -14.0, "code_methode_obs": 0, "libelle_methode_obs": "Mesure", "code_qualification_obs": 16, "libelle_qualification_obs": "Non qualifi\u00e9e", "continuite_obs_hydro": true, "longitude": 5.584492314, "latitude": 43.918773933}, {"code_site": "X3414010", "code_station": "X341401001", "grandeur_hydro": "Q", "date_debut_serie": "2024-09-18T00:00:00Z", "date_fin_serie": "2024-09-18T10:25:00Z", "statut_serie": 4, "code_systeme_alti_serie": 31, "date_obs": "2024-09-18T10:25:00Z", "resultat_obs": 1740.0, "code_methode_obs": 12, "libelle_methode_obs": "Interpolation", "code_qualification_obs": 12, "libelle_qualification_obs": "Douteuse", "continuite_obs_hydro": true, "longitude": 5.584492314, "latitude": 43.918773933}, {"code_site": "X3414010", "code_station": null, "grandeur_hydro": "Q", "date_debut_serie": "2024-09-18T00:00:00Z", "date_fin_serie": "2024-09-18T10:25:00Z", "statut_serie": 4, "code_systeme_alti_serie": 31, "date_obs": "2024-09-18T10:25:00Z", "resultat_obs": 1740.0, "code_methode_obs": 12, "libelle_methode_obs": "Interpolation", "code_qualification_obs": 12, "libelle_qualification_obs": "Douteuse", "continuite_obs_hydro": true, "longitude": 5.5845245, "latitude": 43.918756545}, {"code_site": "X3454010", "code_station": "X345401001", "grandeur_hydro": "H", "date_debut_serie": "2024-09-18T00:00:00Z", "date_fin_serie": "2024-09-18T10:25:00Z", "statut_serie": 4, "code_systeme_alti_serie": 31, "date_obs": "2024-09-18T10:25:00Z", "resultat_obs": -840.0, "code_methode_obs": 0, "libelle_methode_obs": "Mesure", "code_qualification_obs": 16, "libelle_qualification_obs": "Non qualifi\u00e9e", "continuite_obs_hydro": true, "longitude": 5.396465587, "latitude": 43.877366499}, {"code_site": "X3500010", "code_station": "X350001001", "grandeur_hydro": "H", "date_debut_serie": "2024-09-18T00:00:00Z", "date_fin_serie": "2024-09-18T10:25:00Z", "statut_serie": 4, "code_systeme_alti_serie": 31, "date_obs": "2024-09-18T10:25:00Z", "resultat_obs": 1340.0, "code_methode_obs": 0, "libelle_methode_obs": "Mesure", "code_qualification_obs": 16, "libelle_qualification_obs": "Non qualifi\u00e9e", "continuite_obs_hydro": true, "longitude": 4.923197308, "latitude": 43.888799124}, {"code_site": "X3500010", "code_station": "X350001002", "grandeur_hydro": "H", "date_debut_serie": "2024-09-18T00:00:00Z", "date_fin_serie": "2024-09-18T10:25:00Z", "statut_serie": 4, "code_systeme_alti_serie": 31, "date_obs": "2024-09-18T10:25:00Z", "resultat_obs": 3193.0, "code_methode_obs": 0, "libelle_methode_obs": "Mesure", "code_qualification_obs": 16, "libelle_qualification_obs": "Non qualifi\u00e9e", "continuite_obs_hydro": true, "longitude": 4.916563795, "latitude": 43.888784849}, {"code_site": "Y0315020", "code_station": "Y031502001", "grandeur_hydro": "H", "date_debut_serie": "2024-09-18T00:00:00Z", "date_fin_serie": "2024-09-18T10:25:00Z", "statut_serie": 4, "code_systeme_alti_serie": 31, "date_obs": "2024-09-18T10:25:00Z", "resultat_obs": 1873.0, "code_methode_obs": 0, "libelle_methode_obs": "Mesure", "code_qualification_obs": 16, "libelle_qualification_obs": "Non qualifi\u00e9e", "continuite_obs_hydro": true, "longitude": 2.829785482, "latitude": 42.596145655}, {"code_site": "Y0315020", "code_station": "Y031502001", "grandeur_hydro": "Q", "date_debut_serie": "2024-09-18T00:00:00Z", "date_fin_serie": "2024-09-18T10:25:00Z", "statut_serie": 4, "code_systeme_alti_serie": 31, "date_obs": "2024-09-18T10:25:00Z", "resultat_obs": 0.0, "code_methode_obs": 12, "libelle_methode_obs": "Interpolation", "code_qualification_obs": 12, "libelle_qualification_obs": "Douteuse", "continuite_obs_hydro": true, "longitude": 2.829785482, "latitude": 42.596145655}, {"code_site": "Y0315020", "code_station": null, "grandeur_hydro": "Q", "date_debut_serie": "2024-09-18T00:00:00Z", "date_fin_serie": "2024-09-18T10:25:00Z", "statut_serie": 4, "code_systeme_alti_serie": 31, "date_obs": "2024-09-18T10:25:00Z", "resultat_obs": 0.0, "code_methode_obs": 12, "libelle_methode_obs": "Interpolation", "code_qualification_obs": 12, "libelle_qualification_obs": "Douteuse", "continuite_obs_hydro": true, "longitude": 2.830035318, "latitude": 42.596692213}, {"code_site": "Y0325010", "code_station": "Y032501001", "grandeur_hydro": "H", "date_debut_serie": "2024-09-18T00:00:00Z", "date_fin_serie": "2024-09-18T10:25:00Z", "statut_serie": 4, "code_systeme_alti_serie": 31, "date_obs": "2024-09-18T10:25:00Z", "resultat_obs": -5.0, "code_methode_obs": 0, "libelle_methode_obs": "Mesure", "code_qualification_obs": 16, "libelle_qualification_obs": "Non qualifi\u00e9e", "continuite_obs_hydro": true, "longitude": 2.733226216, "latitude": 42.599279857}, {"code_site": "Y0325010", "code_station": "Y032501001", "grandeur_hydro": "Q", "date_debut_serie": "2024-09-18T00:00:00Z", "date_fin_serie": "2024-09-18T10:25:00Z", "statut_serie": 4, "code_systeme_alti_serie": 31, "date_obs": "2024-09-18T10:25:00Z", "resultat_obs": 0.0, "code_methode_obs": 12, "libelle_methode_obs": "Interpolation", "code_qualification_obs": 12, "libelle_qualification_obs": "Douteuse", "continuite_obs_hydro": true, "longitude": 2.733226216, "latitude": 42.599279857}, {"code_site": "Y0325010", "code_station": null, "grandeur_hydro": "Q", "date_debut_serie": "2024-09-18T00:00:00Z", "date_fin_serie": "2024-09-18T10:25:00Z", "statut_serie": 4, "code_systeme_alti_serie": 31, "date_obs": "2024-09-18T10:25:00Z", "resultat_obs": 0.0, "code_methode_obs": 12, "libelle_methode_obs": "Interpolation", "code_qualification_obs": 12, "libelle_qualification_obs": "Douteuse", "continuite_obs_hydro": true, "longitude": 2.732765011, "latitude": 42.598875657}, {"code_site": "Y0334001", "code_station": "Y033400101", "grandeur_hydro": "H", "date_debut_serie": "2024-09-18T00:00:00Z", "date_fin_serie": "2024-09-18T10:25:00Z", "statut_serie": 4, "code_systeme_alti_serie": 31, "date_obs": "2024-09-18T10:25:00Z", "resultat_obs": 1996.0, "code_methode_obs": 0, "libelle_methode_obs": "Mesure", "code_qualification_obs": 16, "libelle_qualification_obs": "Non qualifi\u00e9e", "continuite_obs_hydro": true, "longitude": 2.926916199, "latitude": 42.653230994}, {"code_site": "Y0436405", "code_station": "Y043640501", "grandeur_hydro": "H", "date_debut_serie": "2024-09-18T00:00:00Z", "date_fin_serie": "2024-09-18T10:25:00Z", "statut_serie": 4, "code_systeme_alti_serie": 31, "date_obs": "2024-09-18T10:25:00Z", "resultat_obs": 1158.0, "code_methode_obs": 0, "libelle_methode_obs": "Mesure", "code_qualification_obs": 16, "libelle_qualification_obs": "Non qualifi\u00e9e", "continuite_obs_hydro": true, "longitude": 2.388261892, "latitude": 42.546127115}, {"code_site": "Y0445010", "code_station": "Y044501001", "grandeur_hydro": "H", "date_debut_serie": "2024-09-18T00:00:00Z", "date_fin_serie": "2024-09-18T10:25:00Z", "statut_serie": 4, "code_systeme_alti_serie": 31, "date_obs": "2024-09-18T10:25:00Z", "resultat_obs": 1768.0, "code_methode_obs": 0, "libelle_methode_obs": "Mesure", "code_qualification_obs": 16, "libelle_qualification_obs": "Non qualifi\u00e9e", "continuite_obs_hydro": true, "longitude": 2.422030898, "latitude": 42.632397662}]}